{
  "ob": {
    "s": {
      "typography": {
        "app": {
          "subtitle": {
            "S": {
              "value": {
                "fontFamily": "{ob.p.fontFamily.body}",
                "fontSize": "{ob.p.fontSize.app.sm}",
                "fontWeight": "{ob.p.fontWeight.2}",
                "lineHeight": "{ob.p.lineHeight.body.M.default}",
                "letterSpacing": "{ob.p.letterSpacing.normal}"
              },
              "type": "typography"
            },
            "M": {
              "value": {
                "fontFamily": "{ob.p.fontFamily.body}",
                "fontSize": "{ob.p.fontSize.app.base}",
                "fontWeight": "{ob.p.fontWeight.2}",
                "lineHeight": "{ob.p.lineHeight.body.M.default}",
                "letterSpacing": "{ob.p.letterSpacing.normal}"
              },
              "type": "typography"
            }
          },
          "heading": {
            "H1": {
              "value": {
                "fontFamily": "{ob.p.fontFamily.body}",
                "fontSize": "{ob.p.fontSize.app.6xl}",
                "fontWeight": "{ob.p.fontWeight.2}",
                "letterSpacing": "{ob.p.letterSpacing.narrower}",
                "lineHeight": "{ob.p.lineHeight.headlines.default}"
              },
              "type": "typography"
            },
            "H2": {
              "value": {
                "fontFamily": "{ob.p.fontFamily.body}",
                "fontSize": "{ob.p.fontSize.app.5xl}",
                "fontWeight": "{ob.p.fontWeight.2}",
                "letterSpacing": "{ob.p.letterSpacing.narrower}",
                "lineHeight": "{ob.p.lineHeight.headlines.default}"
              },
              "type": "typography"
            },
            "H3": {
              "value": {
                "fontFamily": "{ob.p.fontFamily.body}",
                "fontSize": "{ob.p.fontSize.app.4xl}",
                "fontWeight": "{ob.p.fontWeight.2}",
                "lineHeight": "{ob.p.lineHeight.headlines.default}",
                "letterSpacing": "{ob.p.letterSpacing.narrower}"
              },
              "type": "typography"
            },
            "H4": {
              "value": {
                "fontFamily": "{ob.p.fontFamily.body}",
                "fontSize": "{ob.p.fontSize.app.3xl}",
                "fontWeight": "{ob.p.fontWeight.2}",
                "lineHeight": "{ob.p.lineHeight.headlines.default}",
                "letterSpacing": "{ob.p.letterSpacing.narrow}"
              },
              "type": "typography"
            },
            "H5": {
              "value": {
                "fontFamily": "{ob.p.fontFamily.body}",
                "fontSize": "{ob.p.fontSize.app.2xl}",
                "fontWeight": "{ob.p.fontWeight.2}",
                "lineHeight": "{ob.p.lineHeight.headlines.default}",
                "letterSpacing": "{ob.p.letterSpacing.normal}"
              },
              "type": "typography"
            },
            "H6": {
              "value": {
                "fontFamily": "{ob.p.fontFamily.body}",
                "fontSize": "{ob.p.fontSize.app.lg}",
                "fontWeight": "{ob.p.fontWeight.2}",
                "letterSpacing": "{ob.p.letterSpacing.normal}",
                "lineHeight": "{ob.p.lineHeight.headlines.default}"
              },
              "type": "typography"
            }
          },
          "label": {
            "S": {
              "regular": {
                "value": {
                  "fontFamily": "{ob.p.fontFamily.body}",
                  "fontSize": "{ob.p.fontSize.app.xs}",
                  "fontWeight": "{ob.p.fontWeight.0}",
                  "lineHeight": "{ob.p.lineHeight.headlines.default}",
                  "letterSpacing": "{ob.p.letterSpacing.normal}"
                },
                "type": "typography"
              },
              "bold": {
                "value": {
                  "fontFamily": "{ob.p.fontFamily.body}",
                  "fontSize": "{ob.p.fontSize.app.xs}",
                  "fontWeight": "{ob.p.fontWeight.2}",
                  "lineHeight": "{ob.p.lineHeight.headlines.default}",
                  "letterSpacing": "{ob.p.letterSpacing.normal}"
                },
                "type": "typography"
              }
            },
            "M": {
              "regular": {
                "value": {
                  "fontFamily": "{ob.p.fontFamily.body}",
                  "fontSize": "{ob.p.fontSize.app.sm}",
                  "fontWeight": "{ob.p.fontWeight.0}",
                  "lineHeight": "{ob.p.lineHeight.body.M.default}",
                  "letterSpacing": "{ob.p.letterSpacing.normal}"
                },
                "type": "typography"
              },
              "bold": {
                "value": {
                  "fontFamily": "{ob.p.fontFamily.body}",
                  "fontSize": "{ob.p.fontSize.app.sm}",
                  "fontWeight": "{ob.p.fontWeight.2}",
                  "lineHeight": "{ob.p.lineHeight.headlines.default}",
                  "letterSpacing": "{ob.p.letterSpacing.normal}"
                },
                "type": "typography"
              }
            }
          },
          "body": {
            "M": {
              "regular": {
                "value": {
                  "fontFamily": "{ob.p.fontFamily.body}",
                  "fontSize": "{ob.p.fontSize.app.base}",
                  "fontWeight": "{ob.p.fontWeight.0}",
                  "lineHeight": "{ob.p.lineHeight.body.L.default}",
                  "letterSpacing": "{ob.p.letterSpacing.normal}"
                },
                "type": "typography"
              },
              "bold": {
                "value": {
                  "fontFamily": "{ob.p.fontFamily.body}",
                  "fontSize": "{ob.p.fontSize.app.base}",
                  "fontWeight": "{ob.p.fontWeight.2}",
                  "lineHeight": "{ob.p.lineHeight.body.M.default}",
                  "letterSpacing": "{ob.p.letterSpacing.normal}"
                },
                "type": "typography"
              }
            },
            "S": {
              "regular": {
                "value": {
                  "fontFamily": "{ob.p.fontFamily.body}",
                  "fontSize": "{ob.p.fontSize.app.sm}",
                  "fontWeight": "{ob.p.fontWeight.0}",
                  "lineHeight": "{ob.p.lineHeight.body.S.default}",
                  "letterSpacing": "{ob.p.letterSpacing.normal}"
                },
                "type": "typography"
              },
              "bold": {
                "value": {
                  "fontFamily": "{ob.p.fontFamily.body}",
                  "fontSize": "{ob.p.fontSize.app.sm}",
                  "fontWeight": "{ob.p.fontWeight.2}",
                  "lineHeight": "{ob.p.lineHeight.body.S.default}",
                  "letterSpacing": "{ob.p.letterSpacing.normal}"
                },
                "type": "typography"
              }
            }
          },
          "headings": {
            "h1": {
              "color": {
                "value": "{tempStandardBody}",
                "type": "color"
              }
            }
          }
        }
      }
    }
  }
}